LICENSE
README.md
setup.py
gtdb_precurate/__init__.py
gtdb_precurate/__main__.py
gtdb_precurate.egg-info/PKG-INFO
gtdb_precurate.egg-info/SOURCES.txt
gtdb_precurate.egg-info/dependency_links.txt
gtdb_precurate.egg-info/entry_points.txt
gtdb_precurate.egg-info/requires.txt
gtdb_precurate.egg-info/top_level.txt
gtdb_precurate/method/__init__.py
gtdb_precurate/method/create_denovo.py
gtdb_precurate/model/__init__.py
gtdb_precurate/model/metadata.py
gtdb_precurate/model/node_label.py
gtdb_precurate/model/ranks.py
gtdb_precurate/model/red_dict.py
gtdb_precurate/model/tree.py
gtdb_precurate/util/__init__.py
gtdb_precurate/util/logger.py
gtdb_precurate/util/tree.py