Metadata-Version: 2.1
Name: gtdb-precurate
Version: 1.0.2
Summary: Automatic pre-curation of GTDB trees.
Home-page: https://github.com/Ecogenomics/gtdb_precurate
Author: Aaron Mussig
Author-email: aaronmussig@gmail.com
Maintainer: Aaron Mussig
Maintainer-email: aaronmussig@gmail.com
License: GPL3
Classifier: Development Status :: 5 - Production/Stable
Classifier: Intended Audience :: Science/Research
Classifier: License :: OSI Approved :: GNU General Public License v3 (GPLv3)
Classifier: Natural Language :: English
Classifier: Programming Language :: Python :: 3
Classifier: Programming Language :: Python :: 3.8
Classifier: Programming Language :: Python :: 3.9
Classifier: Programming Language :: Python :: 3.10
Classifier: Programming Language :: Python :: 3.11
Classifier: Topic :: Scientific/Engineering :: Bio-Informatics
Requires-Python: >=3.8
License-File: LICENSE
Requires-Dist: dendropy>=4.1.0
Requires-Dist: typer[all]
